beaconscanner/__init__.py
beaconscanner/const.py
beaconscanner/device_filters.py
beaconscanner/nrf.py
beaconscanner/scanner.py
beaconscanner/utils.py
beaconscanner-1.2.0.dist-info/LICENSE.txt
beaconscanner-1.2.0.dist-info/METADATA
beaconscanner-1.2.0.dist-info/WHEEL
beaconscanner-1.2.0.dist-info/top_level.txt
beaconscanner-1.2.0.dist-info/RECORD
