Metadata-Version: 2.1
Name: beaconscanner
Version: 1.2.0
Summary: Scan and decode ble data
Home-page: https://github.com/theBASTI0N/beaconscanner
Author: theBASTI0N
Author-email: theBASTI0Ncode@gmail.com
License: MIT
Download-URL: https://github.com/theBASTI0N/beaconscanner/archive/1.2.0.tar.gz
Keywords: BLE,decode,iot
Platform: UNKNOWN
Classifier: Development Status :: 4 - Beta
Classifier: Intended Audience :: Developers
Classifier: Topic :: Software Development :: Build Tools
Classifier: License :: OSI Approved :: MIT License
Classifier: Programming Language :: Python :: 3
Classifier: Programming Language :: Python :: 3.4
Classifier: Programming Language :: Python :: 3.5
Classifier: Programming Language :: Python :: 3.6
Classifier: Programming Language :: Python :: 3.7
Requires-Dist: beacondecoder
Requires-Dist: uptime
Requires-Dist: pyserial
